simpleswap/__init__.py
simpleswap/errors.py
simpleswap/apis/__init__.py
simpleswap/apis/_base.py
simpleswap/apis/_currency.py
simpleswap/apis/_exchange.py
simpleswap/apis/_market.py
simpleswap/apis/_pairs.py
simpleswap-1.0.0.dist-info/LICENCE
simpleswap-1.0.0.dist-info/METADATA
simpleswap-1.0.0.dist-info/WHEEL
simpleswap-1.0.0.dist-info/top_level.txt
simpleswap-1.0.0.dist-info/RECORD
