Metadata-Version: 2.1
Name: simpleswap
Version: 1.0.0
Summary: A package to enable API calls to the simpleswap.io API
Author: drkhedr (Abdelrahman Khedr)
Author-email: <dev@drkhedr.com>
Keywords: python,simpleswap,api,cryptocurrency,exchange,crypto api,simpleswap api,cryptocurrency exchange api
Classifier: Development Status :: 5 - Production/Stable
Classifier: Intended Audience :: Developers
Classifier: Programming Language :: Python :: 3
Classifier: Operating System :: Unix
Classifier: Operating System :: MacOS :: MacOS X
Classifier: Operating System :: Microsoft :: Windows
License-File: LICENCE
Requires-Dist: requests
